pyhrtc/__init__.py
pyhrtc/algorithms.py
pyhrtc/basics.py
pyhrtc/fileio.py
pyhrtc/generator.py
pyhrtc/models.py
pyhrtc/py.typed
pyhrtc/sat.py
pyhrtc/weightedinstance.py
pyhrtc-0.0.12.dist-info/licenses/LICENSE
pyhrtc-0.0.12.dist-info/METADATA
pyhrtc-0.0.12.dist-info/WHEEL
pyhrtc-0.0.12.dist-info/top_level.txt
pyhrtc-0.0.12.dist-info/RECORD
