Metadata-Version: 2.4
Name: pyhrtc
Version: 0.0.12
Summary: A Python package for dealing with the hospital-residents problem with ties and couples.
Author-email: William Pettersson <william@ewpettersson.se>
License:                     GNU GENERAL PUBLIC LICENSE
Project-URL: Homepage, https://gitlab.com/wpettersson/pyhrtc
Project-URL: Repository, https://gitlab.com/wpettersson/pyhrtc
Project-URL: Changelog, https://gitlab.com/wpettersson/pyhrtc/-/blob/main/CHANGELOG.md
Keywords: hr,stable matchings,hospital-residents problem
Classifier: Programming Language :: Python :: 3
Classifier: Programming Language :: Python :: 3.11
Classifier: Programming Language :: Python :: 3.12
Classifier: License :: OSI Approved :: GNU General Public License v3 (GPLv3)
Classifier: Development Status :: 4 - Beta
Classifier: Operating System :: OS Independent
Requires-Python: >=3.11
License-File: LICENSE
Requires-Dist: pulp
Requires-Dist: openpyxl
Requires-Dist: networkx
Provides-Extra: test
Requires-Dist: pytest; extra == "test"
Requires-Dist: mypy>=0.800; extra == "test"
Requires-Dist: black; extra == "test"
Requires-Dist: pytest-cov; extra == "test"
Dynamic: license-file
